LICENSE.txt
MANIFEST.in
README.md
setup.py
ewmh_ext/__init__.py
ewmh_ext.egg-info/PKG-INFO
ewmh_ext.egg-info/SOURCES.txt
ewmh_ext.egg-info/dependency_links.txt
ewmh_ext.egg-info/top_level.txt